nushyax/__init__.py
nushyax/cli.py
nushyax/config.py
nushyax/detector.py
nushyax/dispatcher.py
nushyax/runner.py
nushyax/templates.py
nushyax-0.1.0.dist-info/METADATA
nushyax-0.1.0.dist-info/WHEEL
nushyax-0.1.0.dist-info/entry_points.txt
nushyax-0.1.0.dist-info/top_level.txt
nushyax-0.1.0.dist-info/RECORD
