Metadata-Version: 2.4
Name: nushyax
Version: 0.1.0
Summary: Framework-agnostic developer CLI
Author: Dhanush Ballanki
License: MIT
Requires-Python: >=3.9
Requires-Dist: typer
Requires-Dist: rich
Requires-Dist: pyyaml
